README.txt
gpsbabel.py
setup.py
gpsbabel.egg-info/PKG-INFO
gpsbabel.egg-info/SOURCES.txt
gpsbabel.egg-info/dependency_links.txt
gpsbabel.egg-info/top_level.txt