Metadata-Version: 1.0
Name: gpsbabel
Version: 1.0.0
Summary: Python wrapper for GPSBabel project
Home-page: http://code.google.com/p/python-gpsbabel/
Author: Michael Pedersen
Author-email: m.pedersen@icelus.org 
License: UNKNOWN
Platform: UNKNOWN
